breakwater/__init__.py
breakwater/caisson.py
breakwater/conditions.py
breakwater/design.py
breakwater/interactive.py
breakwater/material.py
breakwater/rubble.py
breakwater/__pycache__/__init__.cpython-37.pyc
breakwater/__pycache__/caisson.cpython-37.pyc
breakwater/__pycache__/conditions.cpython-37.pyc
breakwater/__pycache__/design.cpython-37.pyc
breakwater/__pycache__/interactive.cpython-37.pyc
breakwater/__pycache__/material.cpython-37.pyc
breakwater/__pycache__/rubble.cpython-37.pyc
breakwater/app/__init__.py
breakwater/app/bw-icon.ico
breakwater/app/footer.py
breakwater/app/input.py
breakwater/app/interactive.py
breakwater/app/main.py
breakwater/app/settings.py
breakwater/app/tooltip.py
breakwater/app/__pycache__/__init__.cpython-37.pyc
breakwater/app/__pycache__/footer.cpython-37.pyc
breakwater/app/__pycache__/input.cpython-37.pyc
breakwater/app/__pycache__/interactive.cpython-37.pyc
breakwater/app/__pycache__/main.cpython-37.pyc
breakwater/app/__pycache__/settings.cpython-37.pyc
breakwater/app/__pycache__/tooltip.cpython-37.pyc
breakwater/core/__init__.py
breakwater/core/battjes.py
breakwater/core/bishop.py
breakwater/core/goda.py
breakwater/core/overtopping.py
breakwater/core/scour.py
breakwater/core/soil.py
breakwater/core/stability.py
breakwater/core/substructure.py
breakwater/core/toe.py
breakwater/core/__pycache__/__init__.cpython-37.pyc
breakwater/core/__pycache__/battjes.cpython-37.pyc
breakwater/core/__pycache__/bishop.cpython-37.pyc
breakwater/core/__pycache__/goda.cpython-37.pyc
breakwater/core/__pycache__/overtopping.cpython-37.pyc
breakwater/core/__pycache__/scour.cpython-37.pyc
breakwater/core/__pycache__/soil.cpython-37.pyc
breakwater/core/__pycache__/stability.cpython-37.pyc
breakwater/core/__pycache__/substructure.cpython-37.pyc
breakwater/core/__pycache__/toe.cpython-37.pyc
breakwater/database/__init__.py
breakwater/database/database.csv
breakwater/database/database.py
breakwater/utils/__init__.py
breakwater/utils/_design_explorer.py
breakwater-1.0.dist-info/LICENSE
breakwater-1.0.dist-info/METADATA
breakwater-1.0.dist-info/WHEEL
breakwater-1.0.dist-info/top_level.txt
breakwater-1.0.dist-info/RECORD
