Metadata-Version: 2.1
Name: breakwater
Version: 1.0
Summary: A package for the conceptual design of breakwaters
Home-page: https://github.com/Sander-w/breakwater/
Author: S. Winkel
Author-email: pybreakwater@gmail.com
License: UNKNOWN
Keywords: conceptual design hydraulic engineering breakwaters
Platform: UNKNOWN
Classifier: Programming Language :: Python :: 3
Classifier: Natural Language :: English
Classifier: Operating System :: OS Independent
Classifier: License :: Free for non-commercial use
Requires-Python: >=3.6
Requires-Dist: numpy
Requires-Dist: scipy
Requires-Dist: matplotlib
Requires-Dist: pandas
Requires-Dist: tabulate
